bitshares_pricefeed/__init__.py
bitshares_pricefeed/cli.py
bitshares_pricefeed/ui.py
bitshares_pricefeed/pricefeed.py
bitshares_pricefeed/sources/aex.py
bitshares_pricefeed/sources/bigone.py
bitshares_pricefeed/sources/bitcoinaverage.py
bitshares_pricefeed/sources/bitcoinindonesia.py
bitshares_pricefeed/sources/bitcoinvenezuela.py
bitshares_pricefeed/sources/bitstamp.py
bitshares_pricefeed/sources/bittrex.py
bitshares_pricefeed/sources/btc38.py
bitshares_pricefeed/sources/btcchina.py
bitshares_pricefeed/sources/bter.py
bitshares_pricefeed/sources/chbtc.py
bitshares_pricefeed/sources/coincap.py
bitshares_pricefeed/sources/fixer.py
bitshares_pricefeed/sources/google.py
bitshares_pricefeed/sources/graphene.py
bitshares_pricefeed/sources/huobi.py
bitshares_pricefeed/sources/okcoin.py
bitshares_pricefeed/sources/poloniex.py
bitshares_pricefeed/sources/quandl.py
bitshares_pricefeed/sources/yahoo.py
bitshares_pricefeed/sources/yunbi.py
bitshares_pricefeed/sources/zb.py
bitshares_pricefeed/sources/__init__.py
bitshares_pricefeed/sources/lbank.py
bitshares_pricefeed/sources/coinmarketcap.py
bitshares_pricefeed/sources/currencylayer.py
bitshares_pricefeed/sources/main.py
bitshares_pricefeed/sources/openexchangerate.py
bitshares_pricefeed/examples/XCD.yaml
bitshares_pricefeed/examples/default.yaml
bitshares_pricefeed/examples/fox.yaml
bitshares_pricefeed/examples/hero.yaml
bitshares_pricefeed/examples/hertz.yaml
bitshares/__init__.py
bitshares/aes.py
bitshares/notify.py
bitshares/storage.py
bitshares/amount.py
bitshares/block.py
bitshares/blockchain.py
bitshares/blockchainobject.py
bitshares/committee.py
bitshares/dex.py
bitshares/exceptions.py
bitshares/instance.py
bitshares/memo.py
bitshares/price.py
bitshares/proposal.py
bitshares/utils.py
bitshares/vesting.py
bitshares/wallet.py
bitshares/witness.py
bitshares/worker.py
bitshares/market.py
bitshares/account.py
bitshares/asset.py
bitshares/bitshares.py
bitshares_pricefeed-0.0.10.dist-info/entry_points.txt
bitshares_pricefeed-0.0.10.dist-info/top_level.txt
bitshares_pricefeed-0.0.10.dist-info/METADATA
bitshares_pricefeed-0.0.10.dist-info/DESCRIPTION.rst
bitshares_pricefeed-0.0.10.dist-info/metadata.json
bitshares_pricefeed-0.0.10.dist-info/WHEEL
bitshares_pricefeed-0.0.10.dist-info/RECORD
