Metadata-Version: 2.0
Name: bitshares-pricefeed
Version: 0.0.10
Summary: Command line tool to assist with price feed generation
Home-page: http://www.github.com/xeroc/bitshares-pricefeed
Author: Fabian Schuh
Author-email: Fabian@chainsquad.com
License: UNKNOWN
Download-URL: https://github.com/xeroc/bitshares-pricefeed/tarball/0.0.10
Keywords: bitshares,price,feed,cli
Platform: UNKNOWN
Classifier: License :: OSI Approved :: MIT License
Classifier: Operating System :: OS Independent
Classifier: Programming Language :: Python :: 3
Classifier: Development Status :: 3 - Alpha
Classifier: Intended Audience :: Developers
Requires-Dist: bitshares (>=0.1.9)
Requires-Dist: uptick
Requires-Dist: prettytable
Requires-Dist: click
Requires-Dist: colorama
Requires-Dist: tqdm
Requires-Dist: pyyaml
Requires-Dist: bitcoinaverage
Requires-Dist: quandl
